cdk_foo/__init__.py
cdk_foo/py.typed
cdk_foo/_jsii/__init__.py
cdk_foo/_jsii/cdk-foo@0.2.0.jsii.tgz
cdk_foo-0.2.0.dist-info/LICENSE
cdk_foo-0.2.0.dist-info/METADATA
cdk_foo-0.2.0.dist-info/WHEEL
cdk_foo-0.2.0.dist-info/top_level.txt
cdk_foo-0.2.0.dist-info/RECORD
